<annotation>
	<folder>uvas</folder>
	<filename>525.jpg</filename>
	<path>/home/adele/Descargas/uvas/525.jpg</path>
	<source>
		<database>Unknown</database>
	</source>
	<size>
		<width>4272</width>
		<height>2848</height>
		<depth>3</depth>
	</size>
	<segmented>0</segmented>
	<object>
		<name>Black grapes</name>
		<pose>Unspecified</pose>
		<truncated>0</truncated>
		<difficult>0</difficult>
		<bndbox>
			<xmin>1295</xmin>
			<ymin>140</ymin>
			<xmax>2571</xmax>
			<ymax>2659</ymax>
		</bndbox>
	</object>
</annotation>
