<annotation>
	<folder>uvas</folder>
	<filename>8.jpg</filename>
	<path>/home/adele/Descargas/uvas/8.jpg</path>
	<source>
		<database>Unknown</database>
	</source>
	<size>
		<width>640</width>
		<height>428</height>
		<depth>3</depth>
	</size>
	<segmented>0</segmented>
	<object>
		<name>Green grapes</name>
		<pose>Unspecified</pose>
		<truncated>0</truncated>
		<difficult>0</difficult>
		<bndbox>
			<xmin>270</xmin>
			<ymin>34</ymin>
			<xmax>453</xmax>
			<ymax>341</ymax>
		</bndbox>
	</object>
	<object>
		<name>Green grapes</name>
		<pose>Unspecified</pose>
		<truncated>1</truncated>
		<difficult>0</difficult>
		<bndbox>
			<xmin>151</xmin>
			<ymin>233</ymin>
			<xmax>306</xmax>
			<ymax>428</ymax>
		</bndbox>
	</object>
	<object>
		<name>Green grapes</name>
		<pose>Unspecified</pose>
		<truncated>0</truncated>
		<difficult>0</difficult>
		<bndbox>
			<xmin>32</xmin>
			<ymin>115</ymin>
			<xmax>167</xmax>
			<ymax>214</ymax>
		</bndbox>
	</object>
</annotation>
